<?xml version='1.0' encoding='utf-8'?><!--AUTHOR: Bonux-->
<list>
	<weapon type="mage">
		<stone id="8729">
			<variation id="1">
				<category probability="100">
					<option id="4187" chance="1.1"/>
					<option id="4188" chance="1.1"/>
					<option id="4189" chance="1.1"/>
					<option id="4190" chance="1.1"/>
					<option id="4191" chance="1.1"/>
					<option id="4192" chance="1.1"/>
					<option id="4193" chance="1.1"/>
					<option id="4194" chance="1.1"/>
					<option id="4195" chance="1.1"/>
					<option id="4196" chance="1.1"/>
					<option id="4197" chance="1.1"/>
					<option id="4198" chance="1.1"/>
					<option id="4199" chance="1.1"/>
					<option id="4200" chance="1.1"/>
					<option id="4201" chance="1.1"/>
					<option id="4202" chance="1.1"/>
					<option id="4203" chance="1.1"/>
					<option id="4204" chance="1.1"/>
					<option id="4205" chance="1.1"/>
					<option id="4206" chance="1.1"/>
					<option id="4207" chance="1.1"/>
					<option id="4208" chance="1.1"/>
					<option id="4209" chance="1.1"/>
					<option id="4210" chance="1.1"/>
					<option id="4211" chance="1.1"/>
					<option id="4212" chance="1.1"/>
					<option id="4213" chance="1.1"/>
					<option id="4214" chance="1.1"/>
					<option id="4215" chance="1.1"/>
					<option id="4216" chance="1.1"/>
					<option id="4217" chance="1.1"/>
					<option id="4218" chance="1.1"/>
					<option id="4219" chance="1.1"/>
					<option id="4220" chance="1.1"/>
					<option id="4221" chance="1.1"/>
					<option id="4222" chance="1.1"/>
					<option id="4223" chance="1.1"/>
					<option id="4224" chance="1.1"/>
					<option id="4225" chance="1.1"/>
					<option id="4226" chance="1.1"/>
					<option id="4227" chance="1.1"/>
					<option id="4228" chance="1.1"/>
					<option id="4229" chance="1.1"/>
					<option id="4230" chance="1.1"/>
					<option id="4231" chance="1.1"/>
					<option id="4232" chance="1.1"/>
					<option id="4233" chance="1.1"/>
					<option id="4234" chance="1.1"/>
					<option id="4235" chance="1.1"/>
					<option id="4236" chance="1.1"/>
					<option id="4237" chance="1.1"/>
					<option id="4238" chance="1.1"/>
					<option id="4239" chance="1.1"/>
					<option id="4240" chance="1.1"/>
					<option id="4241" chance="1.1"/>
					<option id="4242" chance="1.1"/>
					<option id="4243" chance="1.1"/>
					<option id="4244" chance="1.1"/>
					<option id="4245" chance="1.1"/>
					<option id="4246" chance="1.1"/>
					<option id="4247" chance="1.1"/>
					<option id="4248" chance="1.1"/>
					<option id="4249" chance="1.1"/>
					<option id="4250" chance="1.1"/>
					<option id="4251" chance="1.1"/>
					<option id="4252" chance="1.1"/>
					<option id="4253" chance="1.1"/>
					<option id="4254" chance="1.1"/>
					<option id="4255" chance="1.1"/>
					<option id="4256" chance="1.1"/>
					<option id="4257" chance="1.1"/>
					<option id="4258" chance="1.1"/>
					<option id="4259" chance="1.1"/>
					<option id="4260" chance="1.1"/>
					<option id="4261" chance="1.1"/>
					<option id="4262" chance="1.1"/>
					<option id="4263" chance="1.1"/>
					<option id="4264" chance="1.1"/>
					<option id="4265" chance="1.1"/>
					<option id="4266" chance="1.1"/>
					<option id="4267" chance="1.1"/>
					<option id="4268" chance="1.1"/>
					<option id="4269" chance="1.1"/>
					<option id="4270" chance="1.1"/>
					<option id="4271" chance="1.1"/>
					<option id="4272" chance="1.1"/>
					<option id="4273" chance="1.1"/>
					<option id="4274" chance="1.1"/>
					<option id="4275" chance="1.1"/>
					<option id="4276" chance="1.1"/>
					<option id="4277" chance="1.0"/>
				</category>
			</variation>
			<variation id="2">
				<category probability="55">
					<option id="11467" chance="7.69"/>
					<option id="11468" chance="7.69"/>
					<option id="11469" chance="7.69"/>
					<option id="11470" chance="7.69"/>
					<option id="11471" chance="7.69"/>
					<option id="11472" chance="7.69"/>
					<option id="11473" chance="7.69"/>
					<option id="11474" chance="7.69"/>
					<option id="11475" chance="7.69"/>
					<option id="11476" chance="7.69"/>
					<option id="11477" chance="7.69"/>
					<option id="11478" chance="7.69"/>
					<option id="11479" chance="7.72"/>
				</category>
				<category probability="35">
					<option id="12377" chance="5.88"/>
					<option id="12378" chance="5.88"/>
					<option id="12379" chance="5.88"/>
					<option id="12380" chance="5.88"/>
					<option id="12381" chance="5.88"/>
					<option id="12382" chance="5.88"/>
					<option id="12383" chance="5.88"/>
					<option id="12384" chance="5.88"/>
					<option id="12385" chance="5.88"/>
					<option id="12386" chance="5.88"/>
					<option id="12387" chance="5.88"/>
					<option id="12388" chance="5.88"/>
					<option id="12389" chance="5.88"/>
					<option id="12390" chance="5.88"/>
					<option id="12391" chance="5.88"/>
					<option id="12392" chance="5.88"/>
					<option id="12393" chance="5.92"/>
				</category>
				<category probability="7">
					<option id="15646" chance="0.93"/>
					<option id="15647" chance="0.93"/>
					<option id="15648" chance="0.93"/>
					<option id="15649" chance="0.93"/>
					<option id="15650" chance="0.93"/>
					<option id="15651" chance="0.93"/>
					<option id="15652" chance="0.93"/>
					<option id="15653" chance="0.93"/>
					<option id="15654" chance="0.93"/>
					<option id="15655" chance="0.93"/>
					<option id="15656" chance="0.93"/>
					<option id="15657" chance="0.93"/>
					<option id="15658" chance="0.93"/>
					<option id="15659" chance="0.93"/>
					<option id="15660" chance="0.93"/>
					<option id="15661" chance="0.93"/>
					<option id="15662" chance="0.93"/>
					<option id="15663" chance="0.93"/>
					<option id="15664" chance="0.93"/>
					<option id="15665" chance="0.93"/>
					<option id="15666" chance="0.93"/>
					<option id="15667" chance="0.93"/>
					<option id="15668" chance="0.93"/>
					<option id="15669" chance="0.93"/>
					<option id="15670" chance="0.93"/>
					<option id="15671" chance="0.93"/>
					<option id="15672" chance="0.93"/>
					<option id="15673" chance="0.93"/>
					<option id="15674" chance="0.93"/>
					<option id="15675" chance="0.93"/>
					<option id="15676" chance="0.93"/>
					<option id="15677" chance="0.93"/>
					<option id="15678" chance="0.93"/>
					<option id="15679" chance="0.93"/>
					<option id="15680" chance="0.93"/>
					<option id="15681" chance="0.93"/>
					<option id="15682" chance="0.93"/>
					<option id="15683" chance="0.93"/>
					<option id="15684" chance="0.93"/>
					<option id="15685" chance="0.93"/>
					<option id="15686" chance="0.93"/>
					<option id="15687" chance="0.93"/>
					<option id="15688" chance="0.93"/>
					<option id="15689" chance="0.93"/>
					<option id="15690" chance="0.93"/>
					<option id="15691" chance="0.93"/>
					<option id="15692" chance="0.93"/>
					<option id="15693" chance="0.93"/>
					<option id="15694" chance="0.93"/>
					<option id="15695" chance="0.93"/>
					<option id="15696" chance="0.93"/>
					<option id="15697" chance="0.93"/>
					<option id="15698" chance="0.93"/>
					<option id="15699" chance="0.93"/>
					<option id="15700" chance="0.93"/>
					<option id="15701" chance="0.93"/>
					<option id="15702" chance="0.93"/>
					<option id="15703" chance="0.93"/>
					<option id="15704" chance="0.93"/>
					<option id="15705" chance="0.93"/>
					<option id="15706" chance="0.93"/>
					<option id="15707" chance="0.93"/>
					<option id="15708" chance="0.93"/>
					<option id="15709" chance="0.93"/>
					<option id="15710" chance="0.93"/>
					<option id="15711" chance="0.93"/>
					<option id="15712" chance="0.93"/>
					<option id="15713" chance="0.93"/>
					<option id="15714" chance="0.93"/>
					<option id="15715" chance="0.93"/>
					<option id="15716" chance="0.93"/>
					<option id="15717" chance="0.93"/>
					<option id="15718" chance="0.93"/>
					<option id="15719" chance="0.93"/>
					<option id="15720" chance="0.93"/>
					<option id="15721" chance="0.93"/>
					<option id="15722" chance="0.93"/>
					<option id="15723" chance="0.93"/>
					<option id="15724" chance="0.93"/>
					<option id="15725" chance="0.93"/>
					<option id="15726" chance="0.93"/>
					<option id="15727" chance="0.93"/>
					<option id="15728" chance="0.93"/>
					<option id="15729" chance="0.93"/>
					<option id="15730" chance="0.93"/>
					<option id="15731" chance="0.93"/>
					<option id="15732" chance="0.93"/>
					<option id="15733" chance="0.93"/>
					<option id="15734" chance="0.93"/>
					<option id="15735" chance="0.93"/>
					<option id="15736" chance="0.93"/>
					<option id="15737" chance="0.93"/>
					<option id="15738" chance="0.93"/>
					<option id="15739" chance="0.93"/>
					<option id="15740" chance="0.93"/>
					<option id="15741" chance="0.93"/>
					<option id="15742" chance="0.93"/>
					<option id="15743" chance="0.93"/>
					<option id="15744" chance="0.93"/>
					<option id="15745" chance="0.93"/>
					<option id="15746" chance="0.93"/>
					<option id="15747" chance="0.93"/>
					<option id="15748" chance="0.93"/>
					<option id="15749" chance="0.93"/>
					<option id="15750" chance="0.93"/>
					<option id="15751" chance="0.93"/>
					<option id="15752" chance="1.42"/>
				</category>
				<category probability="3">
					<option id="15753" chance="1.85"/>
					<option id="15754" chance="1.85"/>
					<option id="15755" chance="1.85"/>
					<option id="15756" chance="1.85"/>
					<option id="15757" chance="1.85"/>
					<option id="15758" chance="1.85"/>
					<option id="15759" chance="1.85"/>
					<option id="15760" chance="1.85"/>
					<option id="15761" chance="1.85"/>
					<option id="15762" chance="1.85"/>
					<option id="15763" chance="1.85"/>
					<option id="15764" chance="1.85"/>
					<option id="15765" chance="1.85"/>
					<option id="15766" chance="1.85"/>
					<option id="15767" chance="1.85"/>
					<option id="15768" chance="1.85"/>
					<option id="15769" chance="1.85"/>
					<option id="15770" chance="1.85"/>
					<option id="15771" chance="1.85"/>
					<option id="15772" chance="1.85"/>
					<option id="15773" chance="1.85"/>
					<option id="15774" chance="1.85"/>
					<option id="15775" chance="1.85"/>
					<option id="15776" chance="1.85"/>
					<option id="15777" chance="1.85"/>
					<option id="15778" chance="1.85"/>
					<option id="15779" chance="1.85"/>
					<option id="15780" chance="1.85"/>
					<option id="15781" chance="1.85"/>
					<option id="15782" chance="1.85"/>
					<option id="15783" chance="1.85"/>
					<option id="15784" chance="1.85"/>
					<option id="15785" chance="1.85"/>
					<option id="15786" chance="1.85"/>
					<option id="15787" chance="1.85"/>
					<option id="15788" chance="1.85"/>
					<option id="15789" chance="1.85"/>
					<option id="15790" chance="1.85"/>
					<option id="15791" chance="1.85"/>
					<option id="15792" chance="1.85"/>
					<option id="15793" chance="1.85"/>
					<option id="15794" chance="1.85"/>
					<option id="15795" chance="1.85"/>
					<option id="15796" chance="1.85"/>
					<option id="15797" chance="1.85"/>
					<option id="15798" chance="1.85"/>
					<option id="15799" chance="1.85"/>
					<option id="15800" chance="1.85"/>
					<option id="15801" chance="1.85"/>
					<option id="15802" chance="1.85"/>
					<option id="15803" chance="1.85"/>
					<option id="15804" chance="1.85"/>
					<option id="15805" chance="1.85"/>
					<option id="15806" chance="1.95"/>
				</category>
			</variation>
		</stone>
	</weapon>
</list>