<list>
    <option_data id="8618">
        <for>
            <add order="0x60" stat="pAtk" value="4.301"/>
            <add order="0x60" stat="mAtk" value="4.95"/>
        </for>
    </option_data>
    <option_data id="8619">
        <for>
            <add order="0x60" stat="pAtk" value="4.301"/>
            <add order="0x60" stat="regHp" value="0.16544"/>
        </for>
    </option_data>
    <option_data id="8620">
        <for>
            <add order="0x60" stat="pAtk" value="4.301"/>
            <add order="0x60" stat="regMp" value="0.07502"/>
        </for>
    </option_data>
    <option_data id="8621">
        <for>
            <add order="0x60" stat="pAtk" value="4.301"/>
            <add order="0x60" stat="regCp" value="0.16544"/>
        </for>
    </option_data>
    <option_data id="8678">
        <for>
            <add order="0x60" stat="mDef" value="6.996"/>
            <add order="0x60" stat="regCp" value="0.1771"/>
        </for>
    </option_data>
    <option_data id="8679">
        <for>
            <add order="0x60" stat="mDef" value="6.996"/>
            <add order="0x60" stat="pEvasRate" value="0.639062"/>
        </for>
    </option_data>
    <option_data id="8680">
        <for>
            <add order="0x60" stat="mDef" value="6.996"/>
            <add order="0x60" stat="pAccCombat" value="0.639062"/>
        </for>
    </option_data>
    <option_data id="8681">
        <for>
            <add order="0x60" stat="mDef" value="6.996"/>
            <add order="0x60" stat="basePCritRate" value="6.919763336"/>
        </for>
    </option_data>
    <option_data id="8682">
        <for>
            <add order="0x60" stat="maxHp" value="35.178"/>
            <add order="0x60" stat="maxMp" value="10.26"/>
        </for>
    </option_data>
    <option_data id="8683">
        <for>
            <add order="0x60" stat="maxHp" value="35.178"/>
            <add order="0x60" stat="maxCp" value="44.164"/>
        </for>
    </option_data>
    <option_data id="8684">
        <for>
            <add order="0x60" stat="maxHp" value="35.178"/>
            <add order="0x60" stat="pAtk" value="4.4"/>
        </for>
    </option_data>
    <option_data id="8685">
        <for>
            <add order="0x60" stat="maxHp" value="35.178"/>
            <add order="0x60" stat="mAtk" value="5.09"/>
        </for>
    </option_data>
    <option_data id="8686">
        <for>
            <add order="0x60" stat="maxHp" value="35.178"/>
            <add order="0x60" stat="regHp" value="0.1771"/>
        </for>
    </option_data>
    <option_data id="8687">
        <for>
            <add order="0x60" stat="maxHp" value="35.178"/>
            <add order="0x60" stat="regMp" value="0.0749"/>
        </for>
    </option_data>
    <option_data id="8688">
        <for>
            <add order="0x60" stat="maxHp" value="35.178"/>
            <add order="0x60" stat="regCp" value="0.1771"/>
        </for>
    </option_data>
    <option_data id="8690">
        <for>
            <add order="0x60" stat="maxHp" value="35.178"/>
            <add order="0x60" stat="pAccCombat" value="0.639062"/>
        </for>
    </option_data>
    <option_data id="8691">
        <for>
            <add order="0x60" stat="maxHp" value="35.178"/>
            <add order="0x60" stat="basePCritRate" value="6.919763336"/>
        </for>
    </option_data>
    <option_data id="8692">
        <for>
            <add order="0x60" stat="maxMp" value="11.286"/>
            <add order="0x60" stat="maxCp" value="44.164"/>
        </for>
    </option_data>
    <option_data id="8693">
        <for>
            <add order="0x60" stat="maxMp" value="11.286"/>
            <add order="0x60" stat="pAtk" value="4.4"/>
        </for>
    </option_data>
    <option_data id="8694">
        <for>
            <add order="0x60" stat="maxMp" value="11.286"/>
            <add order="0x60" stat="mAtk" value="5.09"/>
        </for>
    </option_data>
    <option_data id="8695">
        <for>
            <add order="0x60" stat="maxMp" value="11.286"/>
            <add order="0x60" stat="regHp" value="0.1771"/>
        </for>
    </option_data>
    <option_data id="8696">
        <for>
            <add order="0x60" stat="maxMp" value="11.286"/>
            <add order="0x60" stat="regMp" value="0.0749"/>
        </for>
    </option_data>
    <option_data id="8697">
        <for>
            <add order="0x60" stat="maxMp" value="11.286"/>
            <add order="0x60" stat="regCp" value="0.1771"/>
        </for>
    </option_data>
    <option_data id="8698">
        <for>
            <add order="0x60" stat="maxMp" value="11.286"/>
            <add order="0x60" stat="pEvasRate" value="0.639062"/>
        </for>
    </option_data>
    <option_data id="8699">
        <for>
            <add order="0x60" stat="maxMp" value="11.286"/>
            <add order="0x60" stat="pAccCombat" value="0.639062"/>
        </for>
    </option_data>
</list>
