<?xml version='1.0' encoding='utf-8'?><!--AUTHOR: Bonux-->
<list>
	<weapon type="warrior">
		<stone id="9573">
			<variation id="1">
				<category probability="100">
					<option id="19789" chance="1.1"/>
					<option id="19790" chance="1.1"/>
					<option id="19791" chance="1.1"/>
					<option id="19792" chance="1.1"/>
					<option id="19793" chance="1.1"/>
					<option id="19794" chance="1.1"/>
					<option id="19795" chance="1.1"/>
					<option id="19796" chance="1.1"/>
					<option id="19797" chance="1.1"/>
					<option id="19798" chance="1.1"/>
					<option id="19799" chance="1.1"/>
					<option id="19800" chance="1.1"/>
					<option id="19801" chance="1.1"/>
					<option id="19802" chance="1.1"/>
					<option id="19803" chance="1.1"/>
					<option id="19804" chance="1.1"/>
					<option id="19805" chance="1.1"/>
					<option id="19806" chance="1.1"/>
					<option id="19807" chance="1.1"/>
					<option id="19808" chance="1.1"/>
					<option id="19809" chance="1.1"/>
					<option id="19810" chance="1.1"/>
					<option id="19811" chance="1.1"/>
					<option id="19812" chance="1.1"/>
					<option id="19813" chance="1.1"/>
					<option id="19814" chance="1.1"/>
					<option id="19815" chance="1.1"/>
					<option id="19816" chance="1.1"/>
					<option id="19817" chance="1.1"/>
					<option id="19818" chance="1.1"/>
					<option id="19819" chance="1.1"/>
					<option id="19820" chance="1.1"/>
					<option id="19821" chance="1.1"/>
					<option id="19822" chance="1.1"/>
					<option id="19823" chance="1.1"/>
					<option id="19824" chance="1.1"/>
					<option id="19825" chance="1.1"/>
					<option id="19826" chance="1.1"/>
					<option id="19827" chance="1.1"/>
					<option id="19828" chance="1.1"/>
					<option id="19829" chance="1.1"/>
					<option id="19830" chance="1.1"/>
					<option id="19831" chance="1.1"/>
					<option id="19832" chance="1.1"/>
					<option id="19833" chance="1.1"/>
					<option id="19834" chance="1.1"/>
					<option id="19835" chance="1.1"/>
					<option id="19836" chance="1.1"/>
					<option id="19837" chance="1.1"/>
					<option id="19838" chance="1.1"/>
					<option id="19839" chance="1.1"/>
					<option id="19840" chance="1.1"/>
					<option id="19841" chance="1.1"/>
					<option id="19842" chance="1.1"/>
					<option id="19843" chance="1.1"/>
					<option id="19844" chance="1.1"/>
					<option id="19845" chance="1.1"/>
					<option id="19846" chance="1.1"/>
					<option id="19847" chance="1.1"/>
					<option id="19848" chance="1.1"/>
					<option id="19849" chance="1.1"/>
					<option id="19850" chance="1.1"/>
					<option id="19851" chance="1.1"/>
					<option id="19852" chance="1.1"/>
					<option id="19853" chance="1.1"/>
					<option id="19854" chance="1.1"/>
					<option id="19855" chance="1.1"/>
					<option id="19856" chance="1.1"/>
					<option id="19857" chance="1.1"/>
					<option id="19858" chance="1.1"/>
					<option id="19859" chance="1.1"/>
					<option id="19860" chance="1.1"/>
					<option id="19861" chance="1.1"/>
					<option id="19862" chance="1.1"/>
					<option id="19863" chance="1.1"/>
					<option id="19864" chance="1.1"/>
					<option id="19865" chance="1.1"/>
					<option id="19866" chance="1.1"/>
					<option id="19867" chance="1.1"/>
					<option id="19868" chance="1.1"/>
					<option id="19869" chance="1.1"/>
					<option id="19870" chance="1.1"/>
					<option id="19871" chance="1.1"/>
					<option id="19872" chance="1.1"/>
					<option id="19873" chance="1.1"/>
					<option id="19874" chance="1.1"/>
					<option id="19875" chance="1.1"/>
					<option id="19876" chance="1.1"/>
					<option id="19877" chance="1.1"/>
					<option id="19878" chance="1.1"/>
					<option id="19879" chance="1.0"/>
				</category>
			</variation>
			<variation id="2">
				<category probability="55">
					<option id="20517" chance="7.69"/>
					<option id="20518" chance="7.69"/>
					<option id="20519" chance="7.69"/>
					<option id="20520" chance="7.69"/>
					<option id="20521" chance="7.69"/>
					<option id="20522" chance="7.69"/>
					<option id="20523" chance="7.69"/>
					<option id="20524" chance="7.69"/>
					<option id="20525" chance="7.69"/>
					<option id="20526" chance="7.69"/>
					<option id="20527" chance="7.69"/>
					<option id="20528" chance="7.69"/>
					<option id="20529" chance="7.72"/>
				</category>
				<category probability="35">
					<option id="20608" chance="5.88"/>
					<option id="20609" chance="5.88"/>
					<option id="20610" chance="5.88"/>
					<option id="20611" chance="5.88"/>
					<option id="20612" chance="5.88"/>
					<option id="20613" chance="5.88"/>
					<option id="20614" chance="5.88"/>
					<option id="20615" chance="5.88"/>
					<option id="20616" chance="5.88"/>
					<option id="20617" chance="5.88"/>
					<option id="20618" chance="5.88"/>
					<option id="20619" chance="5.88"/>
					<option id="20620" chance="5.88"/>
					<option id="20621" chance="5.88"/>
					<option id="20622" chance="5.88"/>
					<option id="20623" chance="5.88"/>
					<option id="20624" chance="5.92"/>
				</category>
				<category probability="7">
					<option id="21262" chance="0.93"/>
					<option id="21263" chance="0.93"/>
					<option id="21264" chance="0.93"/>
					<option id="21265" chance="0.93"/>
					<option id="21266" chance="0.93"/>
					<option id="21267" chance="0.93"/>
					<option id="21268" chance="0.93"/>
					<option id="21269" chance="0.93"/>
					<option id="21270" chance="0.93"/>
					<option id="21271" chance="0.93"/>
					<option id="21272" chance="0.93"/>
					<option id="21273" chance="0.93"/>
					<option id="21274" chance="0.93"/>
					<option id="21275" chance="0.93"/>
					<option id="21276" chance="0.93"/>
					<option id="21277" chance="0.93"/>
					<option id="21278" chance="0.93"/>
					<option id="21279" chance="0.93"/>
					<option id="21280" chance="0.93"/>
					<option id="21281" chance="0.93"/>
					<option id="21282" chance="0.93"/>
					<option id="21283" chance="0.93"/>
					<option id="21284" chance="0.93"/>
					<option id="21285" chance="0.93"/>
					<option id="21286" chance="0.93"/>
					<option id="21287" chance="0.93"/>
					<option id="21288" chance="0.93"/>
					<option id="21289" chance="0.93"/>
					<option id="21290" chance="0.93"/>
					<option id="21291" chance="0.93"/>
					<option id="21292" chance="0.93"/>
					<option id="21293" chance="0.93"/>
					<option id="21294" chance="0.93"/>
					<option id="21295" chance="0.93"/>
					<option id="21296" chance="0.93"/>
					<option id="21297" chance="0.93"/>
					<option id="21298" chance="0.93"/>
					<option id="21299" chance="0.93"/>
					<option id="21300" chance="0.93"/>
					<option id="21301" chance="0.93"/>
					<option id="21302" chance="0.93"/>
					<option id="21303" chance="0.93"/>
					<option id="21304" chance="0.93"/>
					<option id="21305" chance="0.93"/>
					<option id="21306" chance="0.93"/>
					<option id="21307" chance="0.93"/>
					<option id="21308" chance="0.93"/>
					<option id="21309" chance="0.93"/>
					<option id="21310" chance="0.93"/>
					<option id="21311" chance="0.93"/>
					<option id="21312" chance="0.93"/>
					<option id="21313" chance="0.93"/>
					<option id="21314" chance="0.93"/>
					<option id="21315" chance="0.93"/>
					<option id="21316" chance="0.93"/>
					<option id="21317" chance="0.93"/>
					<option id="21318" chance="0.93"/>
					<option id="21319" chance="0.93"/>
					<option id="21320" chance="0.93"/>
					<option id="21321" chance="0.93"/>
					<option id="21322" chance="0.93"/>
					<option id="21323" chance="0.93"/>
					<option id="21324" chance="0.93"/>
					<option id="21325" chance="0.93"/>
					<option id="21326" chance="0.93"/>
					<option id="21327" chance="0.93"/>
					<option id="21328" chance="0.93"/>
					<option id="21329" chance="0.93"/>
					<option id="21330" chance="0.93"/>
					<option id="21331" chance="0.93"/>
					<option id="21332" chance="0.93"/>
					<option id="21333" chance="0.93"/>
					<option id="21334" chance="0.93"/>
					<option id="21335" chance="0.93"/>
					<option id="21336" chance="0.93"/>
					<option id="21337" chance="0.93"/>
					<option id="21338" chance="0.93"/>
					<option id="21339" chance="0.93"/>
					<option id="21340" chance="0.93"/>
					<option id="21341" chance="0.93"/>
					<option id="21342" chance="0.93"/>
					<option id="21343" chance="0.93"/>
					<option id="21344" chance="0.93"/>
					<option id="21345" chance="0.93"/>
					<option id="21346" chance="0.93"/>
					<option id="21347" chance="0.93"/>
					<option id="21348" chance="0.93"/>
					<option id="21349" chance="0.93"/>
					<option id="21350" chance="0.93"/>
					<option id="21351" chance="0.93"/>
					<option id="21352" chance="0.93"/>
					<option id="21353" chance="0.93"/>
					<option id="21354" chance="0.93"/>
					<option id="21355" chance="0.93"/>
					<option id="21356" chance="0.93"/>
					<option id="21357" chance="0.93"/>
					<option id="21358" chance="0.93"/>
					<option id="21359" chance="0.93"/>
					<option id="21360" chance="0.93"/>
					<option id="21361" chance="0.93"/>
					<option id="21362" chance="0.93"/>
					<option id="21363" chance="0.93"/>
					<option id="21364" chance="0.93"/>
					<option id="21365" chance="0.93"/>
					<option id="21366" chance="0.93"/>
					<option id="21367" chance="0.93"/>
					<option id="21368" chance="1.42"/>
				</category>
				<category probability="3">
					<option id="21369" chance="1.85"/>
					<option id="21370" chance="1.85"/>
					<option id="21371" chance="1.85"/>
					<option id="21372" chance="1.85"/>
					<option id="21373" chance="1.85"/>
					<option id="21374" chance="1.85"/>
					<option id="21375" chance="1.85"/>
					<option id="21376" chance="1.85"/>
					<option id="21377" chance="1.85"/>
					<option id="21378" chance="1.85"/>
					<option id="21379" chance="1.85"/>
					<option id="21380" chance="1.85"/>
					<option id="21381" chance="1.85"/>
					<option id="21382" chance="1.85"/>
					<option id="21383" chance="1.85"/>
					<option id="21384" chance="1.85"/>
					<option id="21385" chance="1.85"/>
					<option id="21386" chance="1.85"/>
					<option id="21387" chance="1.85"/>
					<option id="21388" chance="1.85"/>
					<option id="21389" chance="1.85"/>
					<option id="21390" chance="1.85"/>
					<option id="21391" chance="1.85"/>
					<option id="21392" chance="1.85"/>
					<option id="21393" chance="1.85"/>
					<option id="21394" chance="1.85"/>
					<option id="21395" chance="1.85"/>
					<option id="21396" chance="1.85"/>
					<option id="21397" chance="1.85"/>
					<option id="21398" chance="1.85"/>
					<option id="21399" chance="1.85"/>
					<option id="21400" chance="1.85"/>
					<option id="21401" chance="1.85"/>
					<option id="21402" chance="1.85"/>
					<option id="21403" chance="1.85"/>
					<option id="21404" chance="1.85"/>
					<option id="21405" chance="1.85"/>
					<option id="21406" chance="1.85"/>
					<option id="21407" chance="1.85"/>
					<option id="21408" chance="1.85"/>
					<option id="21409" chance="1.85"/>
					<option id="21410" chance="1.85"/>
					<option id="21411" chance="1.85"/>
					<option id="21412" chance="1.85"/>
					<option id="21413" chance="1.85"/>
					<option id="21414" chance="1.85"/>
					<option id="21415" chance="1.85"/>
					<option id="21416" chance="1.85"/>
					<option id="21417" chance="1.85"/>
					<option id="21418" chance="1.85"/>
					<option id="21419" chance="1.85"/>
					<option id="21420" chance="1.85"/>
					<option id="21421" chance="1.85"/>
					<option id="21422" chance="1.95"/>
				</category>
			</variation>
		</stone>
	</weapon>
</list>